{"Cluster ID": "3304380016146467847", "Versions": 50, "URL": "http://www.emis.ams.org/journals/LRG/Articles/lrr-2010-3/download/lrr-2010-3Color.pdf", "Year": "2010", "Versions list": "http://scholar.google.com/scholar?cluster=3304380016146467847&hl=en&as_sdt=0,33&sciodt=0,33", "Citations": 802, "Title": "f (R) theories", "Authors": "A De Felice, S Tsujikawa ", "Citation link": null, "Citations list": "http://scholar.google.com/scholar?cites=3304380016146467847&as_sdt=5,33&sciodt=0,33&hl=en", "PDF link": "http://www.emis.ams.org/journals/LRG/Articles/lrr-2010-3/download/lrr-2010-3Color.pdf"}
{"Cluster ID": "13236699625184555085", "Versions": 8, "URL": "http://books.google.com/books?hl=en&lr=&id=UYIs1ndbi38C&oi=fnd&pg=PR9&ots=8m_1MSkfp9&sig=6yoiWH0HdFGdmwqv00RXHE0Gu1U", "Year": "1995", "Versions list": "http://scholar.google.com/scholar?cluster=13236699625184555085&hl=en&as_sdt=0,33&sciodt=0,33", "Citations": 649, "Title": "Gravitation and inertia", "Authors": "I Ciufolini ", "Citation link": null, "Citations list": "http://scholar.google.com/scholar?cites=13236699625184555085&as_sdt=5,33&sciodt=0,33&hl=en", "PDF link": null}
{"Cluster ID": "14265606160750307633", "Versions": 13, "URL": "http://arxiv.org/abs/astro-ph/0001167", "Year": "2000", "Versions list": "http://scholar.google.com/scholar?cluster=14265606160750307633&hl=en&as_sdt=0,33&sciodt=0,33", "Citations": 640, "Title": "Millisecond oscillations in X-ray binaries", "Authors": "M Van der Klis ", "Citation link": null, "Citations list": "http://scholar.google.com/scholar?cites=14265606160750307633&as_sdt=5,33&sciodt=0,33&hl=en", "PDF link": null}
{"Cluster ID": "14110279249614759766", "Versions": 12, "URL": "http://www.sciencedirect.com/science/article/pii/S0370157302002673", "Year": "2002", "Versions list": "http://scholar.google.com/scholar?cluster=14110279249614759766&hl=en&as_sdt=0,33&sciodt=0,33", "Citations": 340, "Title": "Dilaton gravity in two dimensions", "Authors": "D Grumiller, W Kummer, DV Vassilevich ", "Citation link": null, "Citations list": "http://scholar.google.com/scholar?cites=14110279249614759766&as_sdt=5,33&sciodt=0,33&hl=en", "PDF link": null}
{"Cluster ID": "1887245510893068274", "Versions": 4, "URL": "http://rspa.royalsocietypublishing.org/content/381/1780/53.short", "Year": "1982", "Versions list": "http://scholar.google.com/scholar?cluster=1887245510893068274&hl=en&as_sdt=0,33&sciodt=0,33", "Citations": 312, "Title": "Quasi-local mass and angular momentum in general relativity", "Authors": "R Penrose ", "Citation link": null, "Citations list": "http://scholar.google.com/scholar?cites=1887245510893068274&as_sdt=5,33&sciodt=0,33&hl=en", "PDF link": null}
{"Cluster ID": "1562411374718911369", "Versions": 6, "URL": "http://link.springer.com/article/10.1007/BF02828697", "Year": "1988", "Versions list": "http://scholar.google.com/scholar?cluster=1562411374718911369&hl=en&as_sdt=0,33&sciodt=0,33", "Citations": 219, "Title": "Higher-order relativistic periastron advances and binary pulsars", "Authors": "T Damour, G Sch\u00e4eer ", "Citation link": null, "Citations list": "http://scholar.google.com/scholar?cites=1562411374718911369&as_sdt=5,33&sciodt=0,33&hl=en", "PDF link": null}
{"Cluster ID": "17345052744690172019", "Versions": 6, "URL": "http://books.google.com/books?hl=en&lr=&id=Hex3NzVAlvgC&oi=fnd&pg=PA108&ots=45xnJrz4d7&sig=hnOhozcEH0BC18kjRfby5agPGlM", "Year": "2007", "Versions list": "http://scholar.google.com/scholar?cluster=17345052744690172019&hl=en&as_sdt=0,33&sciodt=0,33", "Citations": 161, "Title": "General continuum mechanics", "Authors": "TJ Chung ", "Citation link": null, "Citations list": "http://scholar.google.com/scholar?cites=17345052744690172019&as_sdt=5,33&sciodt=0,33&hl=en", "PDF link": null}
{"Cluster ID": "13505226937986080014", "Versions": 5, "URL": "http://arxiv.org/abs/hep-th/0502193", "Year": "2005", "Versions list": "http://scholar.google.com/scholar?cluster=13505226937986080014&hl=en&as_sdt=0,33&sciodt=0,33", "Citations": 115, "Title": "Lecture notes on Chern-Simons (super-) gravities. (February 2008)", "Authors": "J Zanelli ", "Citation link": null, "Citations list": "http://scholar.google.com/scholar?cites=13505226937986080014&as_sdt=5,33&sciodt=0,33&hl=en", "PDF link": null}
{"Cluster ID": "16591370746482138146", "Versions": 55, "URL": "http://www.emis.ams.org/journals/LRG/Articles/lrr-2010-4/download/lrr-2010-4BW.pdf", "Year": "2010", "Versions list": "http://scholar.google.com/scholar?cluster=16591370746482138146&hl=en&as_sdt=0,33&sciodt=0,33", "Citations": 103, "Title": "The pioneer anomaly", "Authors": "SG Turyshev, VT Toth ", "Citation link": null, "Citations list": "http://scholar.google.com/scholar?cites=16591370746482138146&as_sdt=5,33&sciodt=0,33&hl=en", "PDF link": "http://www.emis.ams.org/journals/LRG/Articles/lrr-2010-4/download/lrr-2010-4BW.pdf"}
{"Cluster ID": "6819705721538462045", "Versions": 8, "URL": "http://journals.aps.org/prd/abstract/10.1103/PhysRevD.38.3000", "Year": "1988", "Versions list": "http://scholar.google.com/scholar?cluster=6819705721538462045&hl=en&as_sdt=0,33&sciodt=0,33", "Citations": 99, "Title": "Spherically symmetric solutions of general second-order gravity", "Authors": "B Whitt ", "Citation link": null, "Citations list": "http://scholar.google.com/scholar?cites=6819705721538462045&as_sdt=5,33&sciodt=0,33&hl=en", "PDF link": null}
