{"Cluster ID": "7422287691854027578", "Versions": 12, "URL": null, "Year": "2012", "Versions list": "http://scholar.google.com/scholar?cluster=7422287691854027578&hl=en&as_sdt=0,5&sciodt=0,5", "Citations": 660, "Title": "Modified gravity and cosmology", "Authors": "T Clifton, PG Ferreira, A Padilla, C Skordis ", "Citation link": null, "Citations list": "http://scholar.google.com/scholar?cites=7422287691854027578&as_sdt=2005&sciodt=0,5&hl=en", "PDF link": null}
{"Cluster ID": "2198438833985681034", "Versions": 11, "URL": "http://iopscience.iop.org/0264-9381/26/16/163001", "Year": "2009", "Versions list": "http://scholar.google.com/scholar?cluster=2198438833985681034&hl=en&as_sdt=0,5&sciodt=0,5", "Citations": 431, "Title": "Quasinormal modes of black holes and black branes", "Authors": "E Berti, V Cardoso, AO Starinets ", "Citation link": null, "Citations list": "http://scholar.google.com/scholar?cites=2198438833985681034&as_sdt=2005&sciodt=0,5&hl=en", "PDF link": null}
{"Cluster ID": "354005273565832870", "Versions": 14, "URL": "http://www.sciencedirect.com/science/article/pii/S0370157399000101", "Year": "1999", "Versions list": "http://scholar.google.com/scholar?cluster=354005273565832870&hl=en&as_sdt=0,5&sciodt=0,5", "Citations": 318, "Title": "Gravitating non-Abelian solitons and black holes with Yang\u2013Mills fields", "Authors": "MS Volkov, DV Galt'sov ", "Citation link": null, "Citations list": "http://scholar.google.com/scholar?cites=354005273565832870&as_sdt=2005&sciodt=0,5&hl=en", "PDF link": null}
{"Cluster ID": "7577819950702351510", "Versions": 9, "URL": "http://journals.aps.org/prd/abstract/10.1103/PhysRevD.62.124004", "Year": "2000", "Versions list": "http://scholar.google.com/scholar?cluster=7577819950702351510&hl=en&as_sdt=0,5&sciodt=0,5", "Citations": 139, "Title": "String-inspired higher-curvature terms and the Randall-Sundrum scenario", "Authors": "NE Mavromatos, J Rizos ", "Citation link": null, "Citations list": "http://scholar.google.com/scholar?cites=7577819950702351510&as_sdt=2005&sciodt=0,5&hl=en", "PDF link": null}
{"Cluster ID": "12094502527810382920", "Versions": 12, "URL": "http://www.sciencedirect.com/science/article/pii/S0370269303005550", "Year": "2003", "Versions list": "http://scholar.google.com/scholar?cluster=12094502527810382920&hl=en&as_sdt=0,5&sciodt=0,5", "Citations": 134, "Title": "Israel conditions for the Gauss\u2013Bonnet theory and the Friedmann equation on the brane universe", "Authors": "E Gravanis, S Willison ", "Citation link": null, "Citations list": "http://scholar.google.com/scholar?cites=12094502527810382920&as_sdt=2005&sciodt=0,5&hl=en", "PDF link": null}
{"Cluster ID": "10698989460529461774", "Versions": 11, "URL": "http://link.springer.com/chapter/10.1007/978-3-540-88460-6_8", "Year": "2009", "Versions list": "http://scholar.google.com/scholar?cluster=10698989460529461774&hl=en&as_sdt=0,5&sciodt=0,5", "Citations": 98, "Title": "Higher order gravity theories and their black hole solutions", "Authors": "C Charmousis ", "Citation link": null, "Citations list": "http://scholar.google.com/scholar?cites=10698989460529461774&as_sdt=2005&sciodt=0,5&hl=en", "PDF link": null}
{"Cluster ID": "5460173503840157968", "Versions": 7, "URL": "http://journals.aps.org/prd/abstract/10.1103/PhysRevD.55.739", "Year": "1997", "Versions list": "http://scholar.google.com/scholar?cluster=5460173503840157968&hl=en&as_sdt=0,5&sciodt=0,5", "Citations": 94, "Title": "Dilatonic black holes with a Gauss-Bonnet term", "Authors": "T Torii, H Yajima, K Maeda ", "Citation link": null, "Citations list": "http://scholar.google.com/scholar?cites=5460173503840157968&as_sdt=2005&sciodt=0,5&hl=en", "PDF link": null}
{"Cluster ID": "17255401633690899107", "Versions": 7, "URL": "http://journals.aps.org/prd/abstract/10.1103/PhysRevD.55.2110", "Year": "1997", "Versions list": "http://scholar.google.com/scholar?cluster=17255401633690899107&hl=en&as_sdt=0,5&sciodt=0,5", "Citations": 90, "Title": "Black hole solutions with dilatonic hair in higher curvature gravity", "Authors": "SO Alexeyev, MV Pomazanov ", "Citation link": null, "Citations list": "http://scholar.google.com/scholar?cites=17255401633690899107&as_sdt=2005&sciodt=0,5&hl=en", "PDF link": null}
{"Cluster ID": "9751592570670668759", "Versions": 8, "URL": "http://www.worldscientific.com/doi/abs/10.1142/S0217732308027497", "Year": "2008", "Versions list": "http://scholar.google.com/scholar?cluster=9751592570670668759&hl=en&as_sdt=0,5&sciodt=0,5", "Citations": 90, "Title": "The Lovelock black holes", "Authors": "C Garraffo, G Giribet ", "Citation link": null, "Citations list": "http://scholar.google.com/scholar?cites=9751592570670668759&as_sdt=2005&sciodt=0,5&hl=en", "PDF link": null}
{"Cluster ID": "5570799327006854396", "Versions": 8, "URL": "http://journals.aps.org/prd/abstract/10.1103/PhysRevD.59.083512", "Year": "1999", "Versions list": "http://scholar.google.com/scholar?cluster=5570799327006854396&hl=en&as_sdt=0,5&sciodt=0,5", "Citations": 71, "Title": "Singularity-free cosmological solutions in quadratic gravity", "Authors": "P Kanti, J Rizos, K Tamvakis ", "Citation link": null, "Citations list": "http://scholar.google.com/scholar?cites=5570799327006854396&as_sdt=2005&sciodt=0,5&hl=en", "PDF link": null}
