{"Cluster ID": "9130043174745814928", "Versions": 15, "URL": "http://www.worldscientific.com/doi/abs/10.1142/S021827180600942X", "Year": "2006", "Versions list": "http://scholar.google.com/scholar?cluster=9130043174745814928&hl=en&as_sdt=0,47&sciodt=0,47", "Citations": 2894, "Title": "Dynamics of dark energy", "Authors": "EJ Copeland, M Sami, S Tsujikawa ", "Citation link": null, "Citations list": "http://scholar.google.com/scholar?cites=9130043174745814928&as_sdt=5,47&sciodt=0,47&hl=en", "PDF link": null}
{"Cluster ID": "3304380016146467847", "Versions": 50, "URL": "http://www.emis.ams.org/journals/LRG/Articles/lrr-2010-3/download/lrr-2010-3Color.pdf", "Year": "2010", "Versions list": "http://scholar.google.com/scholar?cluster=3304380016146467847&hl=en&as_sdt=0,47&sciodt=0,47", "Citations": 804, "Title": "f (R) theories", "Authors": "A De Felice, S Tsujikawa ", "Citation link": null, "Citations list": "http://scholar.google.com/scholar?cites=3304380016146467847&as_sdt=5,47&sciodt=0,47&hl=en", "PDF link": "http://www.emis.ams.org/journals/LRG/Articles/lrr-2010-3/download/lrr-2010-3Color.pdf"}
{"Cluster ID": "3137614785457193698", "Versions": 10, "URL": "http://www.sciencedirect.com/science/article/pii/S0370269305008026", "Year": "2005", "Versions list": "http://scholar.google.com/scholar?cluster=3137614785457193698&hl=en&as_sdt=0,47&sciodt=0,47", "Citations": 153, "Title": "The fate of (phantom) dark energy universe with string curvature corrections", "Authors": "M Sami, A Toporensky, PV Tretjakov, S Tsujikawa ", "Citation link": null, "Citations list": "http://scholar.google.com/scholar?cites=3137614785457193698&as_sdt=5,47&sciodt=0,47&hl=en", "PDF link": null}
{"Cluster ID": "1160336230069194760", "Versions": 9, "URL": "http://www.sciencedirect.com/science/article/pii/S0550321305002087", "Year": "2005", "Versions list": "http://scholar.google.com/scholar?cluster=1160336230069194760&hl=en&as_sdt=0,47&sciodt=0,47", "Citations": 123, "Title": "M-theory inflation from multi M5-brane dynamics", "Authors": "K Becker, M Becker, A Krause ", "Citation link": null, "Citations list": "http://scholar.google.com/scholar?cites=1160336230069194760&as_sdt=5,47&sciodt=0,47&hl=en", "PDF link": null}
{"Cluster ID": "16839449657453194666", "Versions": 12, "URL": "http://iopscience.iop.org/0264-9381/24/21/S04", "Year": "2007", "Versions list": "http://scholar.google.com/scholar?cluster=16839449657453194666&hl=en&as_sdt=0,47&sciodt=0,47", "Citations": 115, "Title": "Lectures on cosmic inflation and its potential stringy realizations", "Authors": "CP Burgess ", "Citation link": null, "Citations list": "http://scholar.google.com/scholar?cites=16839449657453194666&as_sdt=5,47&sciodt=0,47&hl=en", "PDF link": null}
{"Cluster ID": "18443494496708226646", "Versions": 12, "URL": "http://link.springer.com/article/10.1007/s10714-008-0747-9", "Year": "2009", "Versions list": "http://scholar.google.com/scholar?cluster=18443494496708226646&hl=en&as_sdt=0,47&sciodt=0,47", "Citations": 86, "Title": "Some remarks on the dynamical systems approach to fourth order gravity", "Authors": "S Carloni, A Troisi, PKS Dunsby ", "Citation link": null, "Citations list": "http://scholar.google.com/scholar?cites=18443494496708226646&as_sdt=5,47&sciodt=0,47&hl=en", "PDF link": null}
{"Cluster ID": "15561631612004508683", "Versions": 8, "URL": "http://iopscience.iop.org/1126-6708/2007/03/027", "Year": "2007", "Versions list": "http://scholar.google.com/scholar?cluster=15561631612004508683&hl=en&as_sdt=0,47&sciodt=0,47", "Citations": 85, "Title": "Uplifting and inflation with D3 branes", "Authors": "CP Burgess, JM Cline, K Dasgupta\u2026 ", "Citation link": null, "Citations list": "http://scholar.google.com/scholar?cites=15561631612004508683&as_sdt=5,47&sciodt=0,47&hl=en", "PDF link": null}
{"Cluster ID": "886554982081826233", "Versions": 21, "URL": "http://iopscience.iop.org/1126-6708/2006/01/139", "Year": "2006", "Versions list": "http://scholar.google.com/scholar?cluster=886554982081826233&hl=en&as_sdt=0,47&sciodt=0,47", "Citations": 68, "Title": "A new handle on de Sitter compactifications", "Authors": "A Saltman, E Silverstein ", "Citation link": null, "Citations list": "http://scholar.google.com/scholar?cites=886554982081826233&as_sdt=5,47&sciodt=0,47&hl=en", "PDF link": null}
{"Cluster ID": "81232599078144746", "Versions": 11, "URL": "http://journals.aps.org/prd/abstract/10.1103/PhysRevD.72.083509", "Year": "2005", "Versions list": "http://scholar.google.com/scholar?cluster=81232599078144746&hl=en&as_sdt=0,47&sciodt=0,47", "Citations": 62, "Title": "Cosmic acceleration from M theory on twisted spaces", "Authors": "IP Neupane, DL Wiltshire ", "Citation link": null, "Citations list": "http://scholar.google.com/scholar?cites=81232599078144746&as_sdt=5,47&sciodt=0,47&hl=en", "PDF link": null}
{"Cluster ID": "12441001962577228978", "Versions": 13, "URL": "http://journals.aps.org/prd/abstract/10.1103/PhysRevD.82.023519", "Year": "2010", "Versions list": "http://scholar.google.com/scholar?cluster=12441001962577228978&hl=en&as_sdt=0,47&sciodt=0,47", "Citations": 62, "Title": "\u039b CDM universe in f (R) gravity", "Authors": "PKS Dunsby, E Elizalde, R Goswami, S Odintsov\u2026 ", "Citation link": null, "Citations list": "http://scholar.google.com/scholar?cites=12441001962577228978&as_sdt=5,47&sciodt=0,47&hl=en", "PDF link": null}
