{"Cluster ID": "10632375602126838127", "Versions": 15, "URL": "http://www.hindawi.com/journals/ahep/2010/723105/abs/", "Year": "2010", "Versions list": "http://scholar.google.com/scholar?cluster=10632375602126838127&hl=en&as_sdt=0,5&sciodt=0,5", "Citations": 321, "Title": "Holographic duality with a view toward many-body physics", "Authors": "J McGreevy ", "Citation link": null, "Citations list": "http://scholar.google.com/scholar?cites=10632375602126838127&as_sdt=2005&sciodt=0,5&hl=en", "PDF link": null}
{"Cluster ID": "6686884726654106583", "Versions": 9, "URL": "http://iopscience.iop.org/1751-8121/42/50/504005", "Year": "2009", "Versions list": "http://scholar.google.com/scholar?cluster=6686884726654106583&hl=en&as_sdt=0,5&sciodt=0,5", "Citations": 318, "Title": "Entanglement entropy and conformal field theory", "Authors": "P Calabrese, J Cardy ", "Citation link": null, "Citations list": "http://scholar.google.com/scholar?cites=6686884726654106583&as_sdt=2005&sciodt=0,5&hl=en", "PDF link": null}
{"Cluster ID": "7477654632383057591", "Versions": 9, "URL": "http://link.springer.com/article/10.1007/JHEP05(2011)036", "Year": "2011", "Versions list": "http://scholar.google.com/scholar?cluster=7477654632383057591&hl=en&as_sdt=0,5&sciodt=0,5", "Citations": 277, "Title": "Towards a derivation of holographic entanglement entropy", "Authors": "H Casini, M Huerta, RC Myers ", "Citation link": null, "Citations list": "http://scholar.google.com/scholar?cites=7477654632383057591&as_sdt=2005&sciodt=0,5&hl=en", "PDF link": null}
{"Cluster ID": "18390664711257628156", "Versions": 13, "URL": "http://link.springer.com/article/10.1007/JHEP01(2011)125", "Year": "2011", "Versions list": "http://scholar.google.com/scholar?cluster=18390664711257628156&hl=en&as_sdt=0,5&sciodt=0,5", "Citations": 217, "Title": "Holographic c-theorems in arbitrary dimensions", "Authors": "RC Myers, A Sinha ", "Citation link": null, "Citations list": "http://scholar.google.com/scholar?cites=18390664711257628156&as_sdt=2005&sciodt=0,5&hl=en", "PDF link": null}
{"Cluster ID": "9790110484621182857", "Versions": 7, "URL": "http://journals.aps.org/prd/abstract/10.1103/PhysRevD.82.126010", "Year": "2010", "Versions list": "http://scholar.google.com/scholar?cluster=9790110484621182857&hl=en&as_sdt=0,5&sciodt=0,5", "Citations": 175, "Title": "Entanglement Renyi entropies in holographic theories", "Authors": "M Headrick ", "Citation link": null, "Citations list": "http://scholar.google.com/scholar?cites=9790110484621182857&as_sdt=2005&sciodt=0,5&hl=en", "PDF link": null}
{"Cluster ID": "11057313009979293837", "Versions": 7, "URL": "http://link.springer.com/article/10.1007/JHEP01(2012)125", "Year": "2012", "Versions list": "http://scholar.google.com/scholar?cluster=11057313009979293837&hl=en&as_sdt=0,5&sciodt=0,5", "Citations": 153, "Title": "Holographic Fermi surfaces and entanglement entropy", "Authors": "N Ogawa, T Takayanagi, T Ugajin ", "Citation link": null, "Citations list": "http://scholar.google.com/scholar?cites=11057313009979293837&as_sdt=2005&sciodt=0,5&hl=en", "PDF link": null}
{"Cluster ID": "14082013253727304806", "Versions": 7, "URL": "http://link.springer.com/article/10.1007/JHEP08(2013)090", "Year": "2013", "Versions list": "http://scholar.google.com/scholar?cluster=14082013253727304806&hl=en&as_sdt=0,5&sciodt=0,5", "Citations": 152, "Title": "Generalized gravitational entropy", "Authors": "A Lewkowycz, J Maldacena ", "Citation link": null, "Citations list": "http://scholar.google.com/scholar?cites=14082013253727304806&as_sdt=2005&sciodt=0,5&hl=en", "PDF link": null}
{"Cluster ID": "7636704356231133275", "Versions": 17, "URL": "http://journals.aps.org/prl/abstract/10.1103/PhysRevLett.106.191601", "Year": "2011", "Versions list": "http://scholar.google.com/scholar?cluster=7636704356231133275&hl=en&as_sdt=0,5&sciodt=0,5", "Citations": 134, "Title": "Thermalization of strongly coupled field theories", "Authors": "V Balasubramanian, A Bernamonti, J de Boer\u2026 ", "Citation link": null, "Citations list": "http://scholar.google.com/scholar?cites=7636704356231133275&as_sdt=2005&sciodt=0,5&hl=en", "PDF link": null}
{"Cluster ID": "16103784794724476798", "Versions": 15, "URL": "http://journals.aps.org/prd/abstract/10.1103/PhysRevD.84.026010", "Year": "2011", "Versions list": "http://scholar.google.com/scholar?cluster=16103784794724476798&hl=en&as_sdt=0,5&sciodt=0,5", "Citations": 134, "Title": "Holographic thermalization", "Authors": "V Balasubramanian, A Bernamonti, J de Boer\u2026 ", "Citation link": null, "Citations list": "http://scholar.google.com/scholar?cites=16103784794724476798&as_sdt=2005&sciodt=0,5&hl=en", "PDF link": null}
{"Cluster ID": "17393295529887125434", "Versions": 11, "URL": "http://link.springer.com/article/10.1007/JHEP03(2010)131", "Year": "2010", "Versions list": "http://scholar.google.com/scholar?cluster=17393295529887125434&hl=en&as_sdt=0,5&sciodt=0,5", "Citations": 135, "Title": "Holographic superconductor/insulator transition at zero temperature", "Authors": "T Nishioka, S Ryu, T Takayanagi ", "Citation link": null, "Citations list": "http://scholar.google.com/scholar?cites=17393295529887125434&as_sdt=2005&sciodt=0,5&hl=en", "PDF link": null}
