{"Cluster ID": "6681778418204174540", "Versions": 6, "URL": "http://journals.aps.org/prd/abstract/10.1103/PhysRevD.85.124020", "Year": "2012", "Versions list": "http://scholar.google.com/scholar?cluster=6681778418204174540&hl=en&as_sdt=0,44&sciodt=0,44", "Citations": 47, "Title": "Fitting galactic rotation curves with conformal gravity and a global quadratic potential", "Authors": "PD Mannheim, JG O'Brien ", "Citation link": null, "Citations list": "http://scholar.google.com/scholar?cites=6681778418204174540&as_sdt=5,44&sciodt=0,44&hl=en", "PDF link": null}
{"Cluster ID": "15024215961081038755", "Versions": 9, "URL": "http://onlinelibrary.wiley.com/doi/10.1002/sam.11173/full", "Year": "2013", "Versions list": "http://scholar.google.com/scholar?cluster=15024215961081038755&hl=en&as_sdt=0,44&sciodt=0,44", "Citations": 16, "Title": "Measurement errors and scaling relations in astrophysics: a review", "Authors": "S Andreon, M Hurn ", "Citation link": null, "Citations list": "http://scholar.google.com/scholar?cites=15024215961081038755&as_sdt=5,44&sciodt=0,44&hl=en", "PDF link": null}
{"Cluster ID": "15898022808976396710", "Versions": 10, "URL": "http://mnras.oxfordjournals.org/content/426/2/1396.short", "Year": "2012", "Versions list": "http://scholar.google.com/scholar?cluster=15898022808976396710&hl=en&as_sdt=0,44&sciodt=0,44", "Citations": 12, "Title": "High-redshift cosmography: new results and implications for dark energy", "Authors": "M Demianski, E Piedipalumbo\u2026 ", "Citation link": null, "Citations list": "http://scholar.google.com/scholar?cites=15898022808976396710&as_sdt=5,44&sciodt=0,44&hl=en", "PDF link": null}
{"Cluster ID": "2767290085220490855", "Versions": 9, "URL": "http://iopscience.iop.org/1475-7516/2012/02/030", "Year": "2012", "Versions list": "http://scholar.google.com/scholar?cluster=2767290085220490855&hl=en&as_sdt=0,44&sciodt=0,44", "Citations": 11, "Title": "An updated analysis of two classes of f (R) theories of gravity", "Authors": "VF Cardone, S Camera, A Diaferio ", "Citation link": null, "Citations list": "http://scholar.google.com/scholar?cites=2767290085220490855&as_sdt=5,44&sciodt=0,44&hl=en", "PDF link": null}
{"Cluster ID": "4858422929340049660", "Versions": 14, "URL": "http://www.hindawi.com/journals/isrn.astronomy.astrophysics/2011/806549/abs/", "Year": "2011", "Versions list": "http://scholar.google.com/scholar?cluster=4858422929340049660&hl=en&as_sdt=0,44&sciodt=0,44", "Citations": 10, "Title": "Kinematical conformal cosmology: fundamental parameters from astrophysical observations", "Authors": "GU Varieschi ", "Citation link": null, "Citations list": "http://scholar.google.com/scholar?cites=4858422929340049660&as_sdt=5,44&sciodt=0,44&hl=en", "PDF link": null}
{"Cluster ID": "1474262943089086394", "Versions": 9, "URL": "http://mnras.oxfordjournals.org/content/415/4/3580.short", "Year": "2011", "Versions list": "http://scholar.google.com/scholar?cluster=1474262943089086394&hl=en&as_sdt=0,44&sciodt=0,44", "Citations": 10, "Title": "Standardizing the gamma-ray bursts with the Amati Ep, i\u2013Eiso relation: the updated Hubble diagram and implications for cosmography", "Authors": "M Demianski, E Piedipalumbo ", "Citation link": null, "Citations list": "http://scholar.google.com/scholar?cites=1474262943089086394&as_sdt=5,44&sciodt=0,44&hl=en", "PDF link": null}
{"Cluster ID": "14285211085179212207", "Versions": 9, "URL": "http://mnras.oxfordjournals.org/content/441/4/3454.short", "Year": "2014", "Versions list": "http://scholar.google.com/scholar?cluster=14285211085179212207&hl=en&as_sdt=0,44&sciodt=0,44", "Citations": 8, "Title": "High-redshift standard candles: predicted cosmological constraints", "Authors": "AL King, TM Davis, KD Denney\u2026 ", "Citation link": null, "Citations list": "http://scholar.google.com/scholar?cites=14285211085179212207&as_sdt=5,44&sciodt=0,44&hl=en", "PDF link": null}
{"Cluster ID": "11175946687884943311", "Versions": 3, "URL": "http://arxiv.org/abs/1205.2954", "Year": "2012", "Versions list": "http://scholar.google.com/scholar?cluster=11175946687884943311&hl=en&as_sdt=0,44&sciodt=0,44", "Citations": 5, "Title": "Gamma-Ray Bursts are precise distance indicators similar to Type Ia Supernovae?", "Authors": "R Tsutsui, T Nakamura, D Yonetoku\u2026 ", "Citation link": null, "Citations list": "http://scholar.google.com/scholar?cites=11175946687884943311&as_sdt=5,44&sciodt=0,44&hl=en", "PDF link": null}
{"Cluster ID": "15352508209542989072", "Versions": 10, "URL": "http://iopscience.iop.org/1475-7516/2013/06/040", "Year": "2013", "Versions list": "http://scholar.google.com/scholar?cluster=15352508209542989072&hl=en&as_sdt=0,44&sciodt=0,44", "Citations": 3, "Title": "On the null trajectories in conformal Weyl gravity", "Authors": "JR Villanueva, M Olivares ", "Citation link": null, "Citations list": "http://scholar.google.com/scholar?cites=15352508209542989072&as_sdt=5,44&sciodt=0,44&hl=en", "PDF link": null}
{"Cluster ID": "17276203828868845739", "Versions": 7, "URL": "http://www.sciencedirect.com/science/article/pii/S0370269313008423", "Year": "2013", "Versions list": "http://scholar.google.com/scholar?cluster=17276203828868845739&hl=en&as_sdt=0,44&sciodt=0,44", "Citations": 3, "Title": "Test of conformal gravity with astrophysical observations", "Authors": "R Yang, B Chen, H Zhao, J Li, Y Liu ", "Citation link": null, "Citations list": "http://scholar.google.com/scholar?cites=17276203828868845739&as_sdt=5,44&sciodt=0,44&hl=en", "PDF link": null}
