{"Cluster ID": "10004588560477432967", "Versions": 13, "URL": "http://iopscience.iop.org/0264-9381/29/22/224011", "Year": "2012", "Versions list": "http://scholar.google.com/scholar?cluster=10004588560477432967&hl=en&as_sdt=0,5&sciodt=0,5", "Citations": 41, "Title": "Fundamental quantum optics experiments conceivable with satellites\u2014reaching relativistic distances and velocities", "Authors": "D Rideout, T Jennewein\u2026 ", "Citation link": null, "Citations list": "http://scholar.google.com/scholar?cites=10004588560477432967&as_sdt=2005&sciodt=0,5&hl=en", "PDF link": null}
{"Cluster ID": "9901009644340767099", "Versions": 9, "URL": "http://arxiv.org/abs/1210.2223", "Year": "2012", "Versions list": "http://scholar.google.com/scholar?cluster=9901009644340767099&hl=en&as_sdt=0,5&sciodt=0,5", "Citations": 39, "Title": "Observer dependent entanglement", "Authors": "PM Alsing, I Fuentes ", "Citation link": null, "Citations list": "http://scholar.google.com/scholar?cites=9901009644340767099&as_sdt=2005&sciodt=0,5&hl=en", "PDF link": null}
{"Cluster ID": "5256182861280746132", "Versions": 8, "URL": "http://journals.aps.org/prd/abstract/10.1103/PhysRevD.85.081701", "Year": "2012", "Versions list": "http://scholar.google.com/scholar?cluster=5256182861280746132&hl=en&as_sdt=0,5&sciodt=0,5", "Citations": 28, "Title": "Motion generates entanglement", "Authors": "N Friis, DE Bruschi, J Louko, I Fuentes ", "Citation link": null, "Citations list": "http://scholar.google.com/scholar?cites=5256182861280746132&as_sdt=2005&sciodt=0,5&hl=en", "PDF link": null}
{"Cluster ID": "8568887182663156472", "Versions": 7, "URL": "http://iopscience.iop.org/1751-8121/46/16/165303", "Year": "2013", "Versions list": "http://scholar.google.com/scholar?cluster=8568887182663156472&hl=en&as_sdt=0,5&sciodt=0,5", "Citations": 24, "Title": "Time evolution techniques for detectors in relativistic quantum information", "Authors": "DE Bruschi, AR Lee, I Fuentes ", "Citation link": null, "Citations list": "http://scholar.google.com/scholar?cites=8568887182663156472&as_sdt=2005&sciodt=0,5&hl=en", "PDF link": null}
{"Cluster ID": "5837025051664366118", "Versions": 8, "URL": "http://www.tandfonline.com/doi/abs/10.1080/09500340.2012.712725", "Year": "2013", "Versions list": "http://scholar.google.com/scholar?cluster=5837025051664366118&hl=en&as_sdt=0,5&sciodt=0,5", "Citations": 22, "Title": "Entanglement generation in relativistic quantum fields", "Authors": "N Friis, I Fuentes ", "Citation link": null, "Citations list": "http://scholar.google.com/scholar?cites=5837025051664366118&as_sdt=2005&sciodt=0,5&hl=en", "PDF link": null}
{"Cluster ID": "69890704580670888", "Versions": 4, "URL": "http://journals.aps.org/prd/abstract/10.1103/PhysRevD.86.105003", "Year": "2012", "Versions list": "http://scholar.google.com/scholar?cluster=69890704580670888&hl=en&as_sdt=0,5&sciodt=0,5", "Citations": 15, "Title": "Quantum gates and multipartite entanglement resonances realized by nonuniform cavity motion", "Authors": "N Friis, M Huber, I Fuentes, DE Bruschi ", "Citation link": null, "Citations list": "http://scholar.google.com/scholar?cites=69890704580670888&as_sdt=2005&sciodt=0,5&hl=en", "PDF link": null}
{"Cluster ID": "15301424356359022670", "Versions": 10, "URL": "http://iopscience.iop.org/1367-2630/16/5/053041", "Year": "2014", "Versions list": "http://scholar.google.com/scholar?cluster=15301424356359022670&hl=en&as_sdt=0,5&sciodt=0,5", "Citations": 13, "Title": "Testing the effects of gravity and motion on quantum entanglement in space-based experiments", "Authors": "DE Bruschi, C Sab\u00edn, A White, V Baccetti\u2026 ", "Citation link": null, "Citations list": "http://scholar.google.com/scholar?cites=15301424356359022670&as_sdt=2005&sciodt=0,5&hl=en", "PDF link": null}
{"Cluster ID": "13630375488135469393", "Versions": 17, "URL": "http://www.nature.com/srep/2014/140521/srep04996/full/srep04996.html?message-global=remove&WT.mcid=FBKSciReports", "Year": "2014", "Versions list": "http://scholar.google.com/scholar?cluster=13630375488135469393&hl=en&as_sdt=0,5&sciodt=0,5", "Citations": 14, "Title": "Relativistic Quantum Metrology: Exploiting relativity to improve quantum measurement technologies", "Authors": "M Ahmadi, DE Bruschi, C Sab\u00edn, G Adesso, I Fuentes ", "Citation link": null, "Citations list": "http://scholar.google.com/scholar?cites=13630375488135469393&as_sdt=2005&sciodt=0,5&hl=en", "PDF link": null}
{"Cluster ID": "3331086899218276740", "Versions": 10, "URL": "http://iopscience.iop.org/0264-9381/29/22/224002", "Year": "2012", "Versions list": "http://scholar.google.com/scholar?cluster=3331086899218276740&hl=en&as_sdt=0,5&sciodt=0,5", "Citations": 11, "Title": "Continuous variable methods in relativistic quantum information: characterization of quantum and classical correlations of scalar field modes in noninertial frames", "Authors": "G Adesso, S Ragy, D Girolami ", "Citation link": null, "Citations list": "http://scholar.google.com/scholar?cites=3331086899218276740&as_sdt=2005&sciodt=0,5&hl=en", "PDF link": null}
{"Cluster ID": "3329040047006752957", "Versions": 11, "URL": "http://iopscience.iop.org/1367-2630/15/7/073052", "Year": "2013", "Versions list": "http://scholar.google.com/scholar?cluster=3329040047006752957&hl=en&as_sdt=0,5&sciodt=0,5", "Citations": 13, "Title": "Mode-mixing quantum gates and entanglement without particle creation in periodically accelerated cavities", "Authors": "DE Bruschi, J Louko, D Faccio\u2026 ", "Citation link": null, "Citations list": "http://scholar.google.com/scholar?cites=3329040047006752957&as_sdt=2005&sciodt=0,5&hl=en", "PDF link": null}
