{"Cluster ID": "280394607599168761", "Versions": 10, "URL": "http://iopscience.iop.org/1751-8121/42/50/504008", "Year": "2009", "Versions list": "http://scholar.google.com/scholar?cluster=280394607599168761&hl=en&as_sdt=0,5&sciodt=0,5", "Citations": 297, "Title": "Holographic entanglement entropy: an overview", "Authors": "T Nishioka, S Ryu, T Takayanagi ", "Citation link": null, "Citations list": "http://scholar.google.com/scholar?cites=280394607599168761&as_sdt=2005&sciodt=0,5&hl=en", "PDF link": null}
{"Cluster ID": "7477654632383057591", "Versions": 9, "URL": "http://link.springer.com/article/10.1007/JHEP05(2011)036", "Year": "2011", "Versions list": "http://scholar.google.com/scholar?cluster=7477654632383057591&hl=en&as_sdt=0,5&sciodt=0,5", "Citations": 277, "Title": "Towards a derivation of holographic entanglement entropy", "Authors": "H Casini, M Huerta, RC Myers ", "Citation link": null, "Citations list": "http://scholar.google.com/scholar?cites=7477654632383057591&as_sdt=2005&sciodt=0,5&hl=en", "PDF link": null}
{"Cluster ID": "18390664711257628156", "Versions": 13, "URL": "http://link.springer.com/article/10.1007/JHEP01(2011)125", "Year": "2011", "Versions list": "http://scholar.google.com/scholar?cluster=18390664711257628156&hl=en&as_sdt=0,5&sciodt=0,5", "Citations": 217, "Title": "Holographic c-theorems in arbitrary dimensions", "Authors": "RC Myers, A Sinha ", "Citation link": null, "Citations list": "http://scholar.google.com/scholar?cites=18390664711257628156&as_sdt=2005&sciodt=0,5&hl=en", "PDF link": null}
{"Cluster ID": "13753285876908961086", "Versions": 10, "URL": "http://iopscience.iop.org/1751-8121/42/50/504007", "Year": "2009", "Versions list": "http://scholar.google.com/scholar?cluster=13753285876908961086&hl=en&as_sdt=0,5&sciodt=0,5", "Citations": 151, "Title": "Entanglement entropy in free quantum field theory", "Authors": "H Casini, M Huerta ", "Citation link": null, "Citations list": "http://scholar.google.com/scholar?cites=13753285876908961086&as_sdt=2005&sciodt=0,5&hl=en", "PDF link": null}
{"Cluster ID": "9058464383885506015", "Versions": 11, "URL": "http://journals.aps.org/prd/abstract/10.1103/PhysRevD.82.046006", "Year": "2010", "Versions list": "http://scholar.google.com/scholar?cluster=9058464383885506015&hl=en&as_sdt=0,5&sciodt=0,5", "Citations": 146, "Title": "Seeing a c-theorem with holography", "Authors": "RC Myers, A Sinha ", "Citation link": null, "Citations list": "http://scholar.google.com/scholar?cites=9058464383885506015&as_sdt=2005&sciodt=0,5&hl=en", "PDF link": null}
{"Cluster ID": "16079195565081284682", "Versions": 46, "URL": "http://www.emis.ams.org/journals/LRG/Articles/lrr-2011-8/download/lrr-2011-8BW.pdf", "Year": "2011", "Versions list": "http://scholar.google.com/scholar?cluster=16079195565081284682&hl=en&as_sdt=0,5&sciodt=0,5", "Citations": 119, "Title": "Entanglement entropy of black holes", "Authors": "SN Solodukhin ", "Citation link": null, "Citations list": "http://scholar.google.com/scholar?cites=16079195565081284682&as_sdt=2005&sciodt=0,5&hl=en", "PDF link": "http://www.emis.ams.org/journals/LRG/Articles/lrr-2011-8/download/lrr-2011-8BW.pdf"}
{"Cluster ID": "4234886412431304438", "Versions": 8, "URL": "http://link.springer.com/article/10.1007/JHEP04(2011)025", "Year": "2011", "Versions list": "http://scholar.google.com/scholar?cluster=4234886412431304438&hl=en&as_sdt=0,5&sciodt=0,5", "Citations": 116, "Title": "On holographic entanglement entropy and higher curvature gravity", "Authors": "LY Hung, RC Myers, M Smolkin ", "Citation link": null, "Citations list": "http://scholar.google.com/scholar?cites=4234886412431304438&as_sdt=2005&sciodt=0,5&hl=en", "PDF link": null}
{"Cluster ID": "3367700582951745169", "Versions": 7, "URL": "http://journals.aps.org/prd/abstract/10.1103/PhysRevD.85.125016", "Year": "2012", "Versions list": "http://scholar.google.com/scholar?cluster=3367700582951745169&hl=en&as_sdt=0,5&sciodt=0,5", "Citations": 108, "Title": "Renormalization group running of the entanglement entropy of a circle", "Authors": "H Casini, M Huerta ", "Citation link": null, "Citations list": "http://scholar.google.com/scholar?cites=3367700582951745169&as_sdt=2005&sciodt=0,5&hl=en", "PDF link": null}
{"Cluster ID": "5160371911139316633", "Versions": 10, "URL": "http://journals.aps.org/prb/abstract/10.1103/PhysRevB.80.115122", "Year": "2009", "Versions list": "http://scholar.google.com/scholar?cluster=5160371911139316633&hl=en&as_sdt=0,5&sciodt=0,5", "Citations": 97, "Title": "Entanglement entropy in the O (N) model", "Authors": "MA Metlitski, CA Fuertes, S Sachdev ", "Citation link": null, "Citations list": "http://scholar.google.com/scholar?cites=5160371911139316633&as_sdt=2005&sciodt=0,5&hl=en", "PDF link": null}
{"Cluster ID": "3300782286506961008", "Versions": 9, "URL": "http://iopscience.iop.org/1367-2630/13/4/045017", "Year": "2011", "Versions list": "http://scholar.google.com/scholar?cluster=3300782286506961008&hl=en&as_sdt=0,5&sciodt=0,5", "Citations": 95, "Title": "Evolution of holographic entanglement entropy after thermal and electromagnetic quenches", "Authors": "T Albash, CV Johnson ", "Citation link": null, "Citations list": "http://scholar.google.com/scholar?cites=3300782286506961008&as_sdt=2005&sciodt=0,5&hl=en", "PDF link": null}
